tapioca_iugu/__init__.py
tapioca_iugu/resource_mapping.py
tapioca_iugu/tapioca_iugu.py
tapioca_iugu-0.1.3.dist-info/DESCRIPTION.rst
tapioca_iugu-0.1.3.dist-info/METADATA
tapioca_iugu-0.1.3.dist-info/RECORD
tapioca_iugu-0.1.3.dist-info/WHEEL
tapioca_iugu-0.1.3.dist-info/metadata.json
tapioca_iugu-0.1.3.dist-info/top_level.txt
