Metadata-Version: 2.0
Name: tapioca-iugu
Version: 0.1.3
Summary: Iugu API wrapper using tapioca
Home-page: https://github.com/solidarium/tapioca-iugu
Author: Olist Developers
Author-email: developers@olist.com
License: MIT
Keywords: iugu
Platform: UNKNOWN
Classifier: Development Status :: 5 - Production/Stable
Classifier: Intended Audience :: Developers
Classifier: License :: OSI Approved :: MIT License
Classifier: Natural Language :: English
Classifier: Programming Language :: Python :: 2.7
Classifier: Programming Language :: Python :: 3.4
Classifier: Programming Language :: Python :: 3.5
Requires-Dist: tapioca-wrapper (<2)
